<!--  Our one element xml document, describing one instance of a Library object -->
<phoneShop >      <!-- the one libraryobject conatining alle the info -->
	<shopName>My Big PhoneShop</shopName>            <!--  here follow all attributes of the mylibrary object -->
	<address>Lahore, Pakistan</address>
	<contactNumber>03314960870</contactNumber>

    <Phone>                                       <!-- An Instance of a phone -->
		<phoneID>Dostoyjewski</phoneID>              <!-- And its attributes -->
		<IMEI>War and Peace</IMEI>
		<make>12345Sn</make>
		<model>shelf 3 row 4</model>
		<makeYear>001</makeYear>
		<price>001</price>
		<available>001</available>
		<type>001</type>
	</Phone>

    <Phone>                                       <!-- An Instance of a phone -->
		<phoneID>Dostoyjewski</phoneID>              <!-- And its attributes -->
		<IMEI>War and Peace</IMEI>
		<make>12345Sn</make>
		<model>shelf 3 row 4</model>
		<makeYear>001</makeYear>
		<price>001</price>
		<available>001</available>
		<type>001</type>
	</Phone>

    <Phone>                                       <!-- An Instance of a phone -->
		<phoneID>Dostoyjewski</phoneID>              <!-- And its attributes -->
		<IMEI>War and Peace</IMEI>
		<make>12345Sn</make>
		<model>shelf 3 row 4</model>
		<makeYear>001</makeYear>
		<price>001</price>
		<available>001</available>
		<type>001</type>
	</Phone>

    <Phone>                                       <!-- An Instance of a phone -->
		<phoneID>Dostoyjewski</phoneID>              <!-- And its attributes -->
		<IMEI>War and Peace</IMEI>
		<make>12345Sn</make>
		<model>shelf 3 row 4</model>
		<makeYear>001</makeYear>
		<price>001</price>
		<available>001</available>
		<type>001</type>
	</Phone>

	<PhoneSale>
		<receiptID>Joe</receiptID>
		<customerID>Average</customerID>
		<salesManID>25</salesManID>
		<phoneID>J_AV_25</phoneID>
		<saleDate>01012016</saleDate>
	</PhoneSale>

	<PhoneSale>
		<receiptID>Joe</receiptID>
		<customerID>Average</customerID>
		<salesManID>25</salesManID>
		<phoneID>J_AV_25</phoneID>
		<saleDate>01012016</saleDate>
	</PhoneSale>

	<PhoneSale>
		<receiptID>Joe</receiptID>
		<customerID>Average</customerID>
		<salesManID>25</salesManID>
		<phoneID>J_AV_25</phoneID>
		<saleDate>01012016</saleDate>
	</PhoneSale>
    
	<PhoneSale>
		<receiptID>Joe</receiptID>
		<customerID>Average</customerID>
		<salesManID>25</salesManID>
		<phoneID>J_AV_25</phoneID>
		<saleDate>01012016</saleDate>
	</PhoneSale>

	
	<Catalog>
		<name>scifiphones</name>
		<url>www.somwhere.uk/scifi</url>
		<location>upper storie left</location>
		<phones>12345Sn4567#375954Fe4567#</phones>
	</Catalog>
	<Catalog>
		<name>boringphones</name>
		<url>www.somwhere.uk/boring</url>
		<location>lower storie right</location>
		<phones>12345Sn#</phones>
	</Catalog>
	
	<Lending>
		<lendid>001</lendid>
		<memberid>S_SO_68</memberid>
		<isbn>12345Sn</isbn>
		<startdate>01102011</startdate>
		<enddate>22102011</enddate>	
	</Lending>
	<Lending>
		<lendid>002</lendid>
		<memberid>S_SO_68</memberid>
		<isbn>12345XZ</isbn>
		<startdate>01102011</startdate>
		<enddate>22102011</enddate>	
	</Lending>
	<Lending>
		<lendid>003</lendid>
		<memberid>S_SO_68</memberid>
		<isbn>0372</isbn>
		<startdate>01102011</startdate>
		<enddate>22102011</enddate>	
	</Lending>

</phoneShop>     <!-- closing the one libraryobject conatining alle the info -->